adiskreader/__init__.py
adiskreader/_version.py
adiskreader/datasource/__init__.py
adiskreader/datasource/file.py
adiskreader/datasource/gzipfile.py
adiskreader/datasource/smb.py
adiskreader/datasource/ssh.py
adiskreader/disks/__init__.py
adiskreader/disks/raw/__init__.py
adiskreader/disks/vhd/__init__.py
adiskreader/disks/vhd/structures/__init__.py
adiskreader/disks/vhd/structures/dynamicheader.py
adiskreader/disks/vhd/structures/footer.py
adiskreader/disks/vhdx/__init__.py
adiskreader/disks/vhdx/structures/__init__.py
adiskreader/disks/vhdx/structures/headers.py
adiskreader/disks/vmdk/__init__.py
adiskreader/disks/vmdk/structures/__init__.py
adiskreader/disks/vmdk/structures/descriptorfile.py
adiskreader/disks/vmdk/structures/extentdescriptor.py
adiskreader/disks/vmdk/structures/hostedsparseextent.py
adiskreader/examples/__init__.py
adiskreader/examples/console.py
adiskreader/external/__init__.py
adiskreader/external/aiocmd/__init__.py
adiskreader/external/aiocmd/setup.py
adiskreader/external/aiocmd/aiocmd/__init__.py
adiskreader/external/aiocmd/aiocmd/aiocmd.py
adiskreader/external/aiocmd/aiocmd/list_completer.py
adiskreader/external/aiocmd/aiocmd/nested_completer.py
adiskreader/filesystems/__init__.py
adiskreader/filesystems/fat/BootSectorHeader.py
adiskreader/filesystems/fat/DosDateTime.py
adiskreader/filesystems/fat/EightDotThree.py
adiskreader/filesystems/fat/FATDirectoryEntry.py
adiskreader/filesystems/fat/FSInfo.py
adiskreader/filesystems/fat/FatIO.py
adiskreader/filesystems/fat/__init__.py
adiskreader/filesystems/fat/_exceptions.py
adiskreader/filesystems/ntfs/__init__.py
adiskreader/filesystems/ntfs/structures/__init__.py
adiskreader/filesystems/ntfs/structures/file.py
adiskreader/filesystems/ntfs/structures/filerecord.py
adiskreader/filesystems/ntfs/structures/mft.py
adiskreader/filesystems/ntfs/structures/pbs.py
adiskreader/filesystems/ntfs/structures/utils.py
adiskreader/filesystems/ntfs/structures/attributes/__init__.py
adiskreader-0.0.1.dist-info/LICENSE.md
adiskreader-0.0.1.dist-info/METADATA
adiskreader-0.0.1.dist-info/WHEEL
adiskreader-0.0.1.dist-info/entry_points.txt
adiskreader-0.0.1.dist-info/top_level.txt
adiskreader-0.0.1.dist-info/zip-safe
adiskreader-0.0.1.dist-info/RECORD
